django_graph_search/__init__.py
django_graph_search/admin.py
django_graph_search/apps.py
django_graph_search/cache.py
django_graph_search/components.py
django_graph_search/exceptions.py
django_graph_search/factory.py
django_graph_search/graph_resolver.py
django_graph_search/indexer.py
django_graph_search/searcher.py
django_graph_search/settings.py
django_graph_search/signals.py
django_graph_search/urls.py
django_graph_search/utils.py
django_graph_search/views.py
django_graph_search/backends/__init__.py
django_graph_search/backends/base.py
django_graph_search/backends/chromadb.py
django_graph_search/backends/faiss.py
django_graph_search/backends/qdrant.py
django_graph_search/embeddings/__init__.py
django_graph_search/embeddings/base.py
django_graph_search/embeddings/sentence_transformers.py
django_graph_search/management/__init__.py
django_graph_search/management/commands/__init__.py
django_graph_search/management/commands/build_search_index.py
django_graph_search/management/commands/clear_search_index.py
django_graph_search/management/commands/search_index_status.py
django_graph_search/static/django_graph_search/css/search.css
django_graph_search/static/django_graph_search/js/search.js
django_graph_search/templates/django_graph_search/admin/search.html
django_graph_search-0.1.2.dist-info/licenses/LICENSE
django_graph_search-0.1.2.dist-info/METADATA
django_graph_search-0.1.2.dist-info/WHEEL
django_graph_search-0.1.2.dist-info/top_level.txt
django_graph_search-0.1.2.dist-info/RECORD
