Metadata-Version: 2.4
Name: django-graph-search
Version: 0.1.2
Summary: Vector search for Django models with graph relations
Home-page: https://example.com/django-graph-search
Author: Your Name
License: MIT
Classifier: Framework :: Django
Classifier: Framework :: Django :: 4
Classifier: Framework :: Django :: 4.2
Classifier: Programming Language :: Python :: 3
Classifier: Programming Language :: Python :: 3.10
Classifier: Programming Language :: Python :: 3.11
Classifier: Programming Language :: Python :: 3.12
Classifier: License :: OSI Approved :: MIT License
Requires-Python: >=3.10
License-File: LICENSE
Requires-Dist: django>=4.2
Requires-Dist: sentence-transformers>=2.2.2
Provides-Extra: chromadb
Requires-Dist: chromadb>=0.5.0; extra == "chromadb"
Provides-Extra: faiss
Requires-Dist: faiss-cpu>=1.7.4; extra == "faiss"
Provides-Extra: qdrant
Requires-Dist: qdrant-client>=1.6.0; extra == "qdrant"
Provides-Extra: test
Requires-Dist: pytest>=9.0.0; extra == "test"
Provides-Extra: all
Requires-Dist: chromadb>=0.5.0; extra == "all"
Requires-Dist: faiss-cpu>=1.7.4; extra == "all"
Requires-Dist: qdrant-client>=1.6.0; extra == "all"
Dynamic: license-file
